test101/__init__.py
test101-0.0.1.dist-info/LICENSE
test101-0.0.1.dist-info/METADATA
test101-0.0.1.dist-info/WHEEL
test101-0.0.1.dist-info/top_level.txt
test101-0.0.1.dist-info/RECORD
