Metadata-Version: 2.1
Name: test101
Version: 0.0.1
Summary: A small test package
Home-page: https://github.com/pypa/sampleproject
Author: GuiGuy
Author-email: 2darbyr@gmail.com
License: UNKNOWN
Platform: UNKNOWN
Classifier: Programming Language :: Python :: 3
Classifier: Operating System :: OS Independent
Requires-Python: >=3.8
